.flake8
.gitignore
LICENSE.txt
README.md
setup.cfg
setup.py
schulze/__init__.py
schulze/convert.py
schulze/types.py
schulze.egg-info/PKG-INFO
schulze.egg-info/SOURCES.txt
schulze.egg-info/dependency_links.txt
schulze.egg-info/top_level.txt
tests/schulze_test.py