Metadata-Version: 1.1
Name: schulze
Version: 0.1
Summary: Implementation of the Schulze method for ranking candidates
Home-page: https://github.com/stadtgestalten/schulze-method
Author: Konrad Mohrfeldt <konrad.mohrfeldt@farbdev.org>, Michael G. Parker
Author-email: UNKNOWN
License: Apache Software License
Keywords: schulze ranking vote election
Platform: UNKNOWN
Classifier: Development Status :: 5 - Production/Stable
Classifier: License :: OSI Approved :: Apache Software License
Classifier: Programming Language :: Python :: 3
